i_dot_ai_utilities/__init__.py
i_dot_ai_utilities/auth/__init__.py
i_dot_ai_utilities/auth/auth_api.py
i_dot_ai_utilities/auth/exceptions.py
i_dot_ai_utilities/auth/py.typed
i_dot_ai_utilities/file_store/README.md
i_dot_ai_utilities/file_store/__init__.py
i_dot_ai_utilities/file_store/factory.py
i_dot_ai_utilities/file_store/main.py
i_dot_ai_utilities/file_store/settings.py
i_dot_ai_utilities/file_store/aws_s3/main.py
i_dot_ai_utilities/file_store/azure_blob_storage/main.py
i_dot_ai_utilities/file_store/gcp_cloud_storage/main.py
i_dot_ai_utilities/file_store/types/file_store_destination_enum.py
i_dot_ai_utilities/file_store/types/kwargs_dicts.py
i_dot_ai_utilities/litellm/README.md
i_dot_ai_utilities/litellm/__init__.py
i_dot_ai_utilities/litellm/exceptions.py
i_dot_ai_utilities/litellm/main.py
i_dot_ai_utilities/litellm/settings.py
i_dot_ai_utilities/litellm/tests/__init__.py
i_dot_ai_utilities/litellm/tests/conftest.py
i_dot_ai_utilities/litellm/tests/test_queries.py
i_dot_ai_utilities/logging/README.md
i_dot_ai_utilities/logging/__init__.py
i_dot_ai_utilities/logging/processor_helper.py
i_dot_ai_utilities/logging/py.typed
i_dot_ai_utilities/logging/structured_logger.py
i_dot_ai_utilities/logging/enrichers/context_extractor.py
i_dot_ai_utilities/logging/enrichers/enrichment_provider.py
i_dot_ai_utilities/logging/enrichers/fargate_enricher.py
i_dot_ai_utilities/logging/enrichers/fastapi_enricher.py
i_dot_ai_utilities/logging/enrichers/lambda_context_enricher.py
i_dot_ai_utilities/logging/enrichers/lambda_environment_enricher.py
i_dot_ai_utilities/logging/types/__init__.py
i_dot_ai_utilities/logging/types/base_context.py
i_dot_ai_utilities/logging/types/context_enrichment_options.py
i_dot_ai_utilities/logging/types/context_fields.py
i_dot_ai_utilities/logging/types/enrichment_types.py
i_dot_ai_utilities/logging/types/fargate_enrichment_schema.py
i_dot_ai_utilities/logging/types/fastapi_enrichment_schema.py
i_dot_ai_utilities-0.4.4.dist-info/METADATA
i_dot_ai_utilities-0.4.4.dist-info/WHEEL
i_dot_ai_utilities-0.4.4.dist-info/licenses/LICENSE
i_dot_ai_utilities-0.4.4.dist-info/RECORD
