Metadata-Version: 2.4
Name: i-dot-ai-utilities
Version: 0.4.4
Summary: Utilities for i.ai to use
Project-URL: Homepage, https://github.com/i-dot-ai/i-dot-ai-utilities
Author-email: i-dot-ai-packages <packages@cabinetoffice.gov.uk>
License: MIT
License-File: LICENSE
Keywords: package,python
Classifier: Development Status :: 2 - Pre-Alpha
Classifier: Environment :: Web Environment
Classifier: Intended Audience :: Developers
Classifier: License :: OSI Approved :: MIT License
Classifier: Operating System :: OS Independent
Classifier: Programming Language :: Python
Classifier: Programming Language :: Python :: 3.10
Classifier: Programming Language :: Python :: 3.11
Classifier: Programming Language :: Python :: 3.12
Classifier: Programming Language :: Python :: 3.13
Requires-Python: <4.0,>=3.10
Requires-Dist: pydantic-settings>=2.10.1
Requires-Dist: pydantic>=2.11.9
Requires-Dist: structlog>=25.4.0
Requires-Dist: typing-extensions>=4.0.0
Provides-Extra: all
Requires-Dist: azure-core>=1.35.1; extra == 'all'
Requires-Dist: azure-storage-blob>=12.26.0; extra == 'all'
Requires-Dist: boto3-stubs[s3]>=1.40.41; extra == 'all'
Requires-Dist: boto3>=1.40.41; extra == 'all'
Requires-Dist: ecologits>=0.8.2; extra == 'all'
Requires-Dist: google-cloud-storage>=3.3.1; extra == 'all'
Requires-Dist: langfuse>=3.4.0; extra == 'all'
Requires-Dist: litellm>=1.77.1; extra == 'all'
Requires-Dist: minio>=7.2.15; extra == 'all'
Requires-Dist: rapidfuzz>=3.14.1; extra == 'all'
Requires-Dist: requests>=2.32.3; extra == 'all'
Provides-Extra: auth
Requires-Dist: requests>=2.32.3; extra == 'auth'
Provides-Extra: dev
Requires-Dist: mypy>=1.15.0; extra == 'dev'
Requires-Dist: pytest-cov>=6.1.1; extra == 'dev'
Requires-Dist: pytest>=8.3.5; extra == 'dev'
Requires-Dist: ruff>=0.12.2; extra == 'dev'
Provides-Extra: file-store
Requires-Dist: azure-core>=1.35.1; extra == 'file-store'
Requires-Dist: azure-storage-blob>=12.26.0; extra == 'file-store'
Requires-Dist: boto3-stubs[s3]>=1.40.41; extra == 'file-store'
Requires-Dist: boto3>=1.40.41; extra == 'file-store'
Requires-Dist: google-cloud-storage>=3.3.1; extra == 'file-store'
Requires-Dist: grpcio-status>=1.76.0; extra == 'file-store'
Requires-Dist: minio>=7.2.15; extra == 'file-store'
Provides-Extra: litellm
Requires-Dist: ecologits>=0.8.2; extra == 'litellm'
Requires-Dist: langfuse>=3.4.0; extra == 'litellm'
Requires-Dist: litellm>=1.79.0; extra == 'litellm'
Requires-Dist: opentelemetry-api>=1.37.0; extra == 'litellm'
Requires-Dist: opentelemetry-exporter-otlp>=1.37.0; extra == 'litellm'
Requires-Dist: opentelemetry-sdk>=1.37.0; extra == 'litellm'
Requires-Dist: rapidfuzz>=3.14.1; extra == 'litellm'
Requires-Dist: requests>=2.32.3; extra == 'litellm'
Provides-Extra: metrics
